pun_cli/__init__.py
pun_cli/__main__.py
pun_cli/cli.py
pun_cli/pun_generator.py
pun_cli-0.1.4.dist-info/LICENSE
pun_cli-0.1.4.dist-info/METADATA
pun_cli-0.1.4.dist-info/WHEEL
pun_cli-0.1.4.dist-info/entry_points.txt
pun_cli-0.1.4.dist-info/RECORD
