Metadata-Version: 2.1
Name: pun-cli
Version: 0.1.4
Summary: Pun-CLI: Because you can't resist a good pun. Generate hilarious puns from our pun repository or contribute your own puns to the list. Pun-CLI, the command-line tool you never knew you needed.
License: MIT
Author: Vahid Al
Author-email: thevahidal@gmail.com
Requires-Python: >=3.10,<4.0
Classifier: Development Status :: 3 - Alpha
Classifier: Environment :: Console
Classifier: Intended Audience :: Developers
Classifier: License :: OSI Approved :: MIT License
Classifier: Natural Language :: English
Classifier: Operating System :: OS Independent
Classifier: Programming Language :: Python :: 3
Classifier: Programming Language :: Python :: 3.10
Classifier: Programming Language :: Python :: 3.11
Classifier: Programming Language :: Python :: 3
Classifier: Programming Language :: Python :: 3.10
Classifier: Topic :: Software Development :: Libraries :: Python Modules
Classifier: Topic :: Utilities
Requires-Dist: cowsay (>=5.0,<6.0)
Requires-Dist: requests (>=2.28.2,<3.0.0)
